config_bat/__init__.py
config_bat/config.py
config_bat-0.4.1.dist-info/LICENSE
config_bat-0.4.1.dist-info/METADATA
config_bat-0.4.1.dist-info/WHEEL
config_bat-0.4.1.dist-info/top_level.txt
config_bat-0.4.1.dist-info/RECORD
