Metadata-Version: 2.1
Name: config-bat
Version: 0.4.1
Summary: A package to share config accross modules
Home-page: UNKNOWN
Author: Ninh Chu
Author-email: chulucninh09@gmail.com
License: UNKNOWN
Platform: UNKNOWN
Classifier: Programming Language :: Python :: 3
Classifier: License :: OSI Approved :: MIT License
Classifier: Operating System :: OS Independent
